cft_analysis/__init__.py
cft_analysis/_types.py
cft_analysis/datasets/__init__.py
cft_analysis/datasets/_cft_dataset_processed.py
cft_analysis/datasets/_cft_dataset_raw.py
cft_analysis/datasets/helper.py
cft_analysis/feature_extraction/__init__.py
cft_analysis/feature_extraction/cft.py
cft_analysis/feature_extraction/hrv.py
cft_analysis/utils/__init__.py
cft_analysis/utils/data_reshaping.py
cft_analysis-1.2.0.dist-info/METADATA
cft_analysis-1.2.0.dist-info/WHEEL
cft_analysis-1.2.0.dist-info/LICENSE
cft_analysis-1.2.0.dist-info/RECORD
