Metadata-Version: 2.1
Name: cft-analysis
Version: 1.2.0
Summary: Package for the analysis of Cold Face Test Data.
Home-page: https://github.com/mad-lab-fau/cft-analysis
License: MIT
Author: Robert Richer
Author-email: robert.richer@fau.de
Requires-Python: >=3.8,<3.11
Classifier: License :: OSI Approved :: MIT License
Classifier: Programming Language :: Python :: 3
Classifier: Programming Language :: Python :: 3.8
Classifier: Programming Language :: Python :: 3.9
Classifier: Programming Language :: Python :: 3.10
Requires-Dist: biopsykit[jupyter] (>=0.6,<0.7)
Requires-Dist: tpcp (>=0.9.0,<0.10.0)
Project-URL: Repository, https://github.com/mad-lab-fau/cft-analysis
